icoutil/IcoFile.py
icoutil/__init__.py
icoutil/__main__.py
icoutil-1.0.1.dist-info/LICENSE
icoutil-1.0.1.dist-info/METADATA
icoutil-1.0.1.dist-info/WHEEL
icoutil-1.0.1.dist-info/entry_points.txt
icoutil-1.0.1.dist-info/top_level.txt
icoutil-1.0.1.dist-info/RECORD
