Metadata-Version: 2.1
Name: icoutil
Version: 1.0.1
Summary: Simple Python library to create .ICO files (Windows icon file format).
Author-email: Olivier Cléro <oclero@protonmail.com>
License: MIT License
Project-URL: Homepage, https://github.com/oclero/icoutil
Project-URL: Issues, https://github.com/oclero/icoutil/issues
Project-URL: Repository, https://github.com/oclero/icoutil.git
Project-URL: Changelog, https://github.com/oclero/icoutil/blob/master/CHANGELOG.md
Keywords: windows,icon,.ico
Classifier: Development Status :: 5 - Production/Stable
Classifier: Intended Audience :: Developers
Classifier: Topic :: Software Development :: Build Tools
Classifier: Programming Language :: Python :: 3
Classifier: License :: OSI Approved :: MIT License
Classifier: Operating System :: OS Independent
Requires-Python: >=3
License-File: LICENSE
Requires-Dist: pillow
